nirsimple/__init__.py
nirsimple/preprocessing.py
nirsimple/processing.py
nirsimple/tables/cope.csv
nirsimple/tables/gratzer.csv
nirsimple/tables/moaveni.csv
nirsimple/tables/takatani.csv
nirsimple/tables/wray.csv
nirsimple-0.1.6.dist-info/LICENSE
nirsimple-0.1.6.dist-info/METADATA
nirsimple-0.1.6.dist-info/WHEEL
nirsimple-0.1.6.dist-info/top_level.txt
nirsimple-0.1.6.dist-info/RECORD
