Metadata-Version: 2.1
Name: nirsimple
Version: 0.1.6
Summary: fNIRS signal processing simplified
Home-page: https://github.com/HanBnrd/NIRSimple
Author: Johann Benerradi
Author-email: johann.benerradi@gmail.com
License: MIT
Classifier: Programming Language :: Python :: 3
Classifier: License :: OSI Approved :: MIT License
Classifier: Operating System :: OS Independent
Requires-Python: >=3.6
License-File: LICENSE
Requires-Dist: numpy
Requires-Dist: pandas
Requires-Dist: scipy
